Metadata-Version: 2.1
Name: img2char
Version: 0.0.1
Summary: This is an Example package
Author: Billy
Author-email: liangbilin0324@163.com
License: UNKNOWN
Platform: UNKNOWN
